{
    "users":[
        {
            "username": "John",
            "password": "6e0b7076126a29d5dfcbd54835387b7b",
            "devices": [
                {
                    "name": "AC unit",
                    "data": "0xE0E040BF"
                },
                {
                    "name": "TV",
                    "data": "0xA3E621DB"
                }
            ]
        },
        {
            "username": "Bob",
            "password": "2acba7f51acfd4fd5102ad090fc612ee",
            "devices": [
                {
                    "name": "AC unit",
                    "data": "0xE0E040BF"
                },
                {
                    "name": "Heating",
                    "data": "0xB4A321AC"
                }
            ]
        }
    ]
}